<configuration>
    <property>
        <name>fs.s3.impl</name>
        <value>org.apache.hadoop.fs.s3a.S3AFileSystem</value>
    </property>
    <property>
        <name>fs.s3a.impl</name>
        <value>org.apache.hadoop.fs.s3a.S3AFileSystem</value>
    </property>
    <property>
        <name>fs.s3a.aws.credentials.provider</name>
        <value>com.amazonaws.auth.DefaultAWSCredentialsProviderChain</value>
    </property>
    <property>
        <name>fs.s3.aws.credentials.provider</name>
        <value>com.amazonaws.auth.DefaultAWSCredentialsProviderChain</value>
    </property>

    <property>
        <name>fs.s3a.connection.ssl.enabled</name>
        <value>false</value>
    </property>

    <property>
        <name>fs.s3a.endpoint</name>
        <value>http://minio:9000</value>
    </property>
</configuration>